csv_to_db_converter/__init__.py
csv_to_db_converter/crud_operation_db.py
csv_to_db_converter/csv_db.py
csv_to_db_converter/upload_file.py
csv_to_db_converter_saatwikmehta-0.1.0.dist-info/LICENSE
csv_to_db_converter_saatwikmehta-0.1.0.dist-info/METADATA
csv_to_db_converter_saatwikmehta-0.1.0.dist-info/WHEEL
csv_to_db_converter_saatwikmehta-0.1.0.dist-info/top_level.txt
csv_to_db_converter_saatwikmehta-0.1.0.dist-info/RECORD
