Metadata-Version: 2.1
Name: csv-to-db-converter-saatwikmehta
Version: 0.1.0
Summary: This package is useful for someone who wants to make changes inside his CSV files.It creates a local server that provides the functionality of file upload to dbReading the data inside the db table created using the name of the file and applying CRUD operations as well.
Home-page: https://github.com/Saatwik-Mehta/csv_to_db_pkg
Author: Saatwik Mehta
Author-email: saatwikmehta@gmail.com
License: UNKNOWN
Project-URL: Bug Tracker, https://github.com/Saatwik-Mehta/csv_to_db_pkg/issues
Platform: UNKNOWN
Classifier: Programming Language :: Python :: 3
Classifier: License :: OSI Approved :: MIT License
Classifier: Operating System :: OS Independent
Requires-Python: >=3.7
License-File: LICENSE
Requires-Dist: mysql-connector-python
Requires-Dist: Jinja2
Requires-Dist: pandas
